Metadata-Version: 1.1
Name: RecSysDemoii
Version: 0.0.3
Summary: Recomendation System Demo
Home-page: UNKNOWN
Author: Remadnia Ouahiba
Author-email: remadniahiba3@gmail.com
License: MIT
Keywords: Recomndation
Platform: UNKNOWN
Classifier: Development Status :: 5 - Production/Stable
Classifier: Intended Audience :: Education
Classifier: Operating System :: Microsoft :: Windows :: Windows 10
Classifier: License :: OSI Approved :: MIT License
Classifier: Programming Language :: Python :: 3
